Dhantri/__init__.py
Dhantri-0.1.dist-info/LICENCE.txt
Dhantri-0.1.dist-info/METADATA
Dhantri-0.1.dist-info/WHEEL
Dhantri-0.1.dist-info/top_level.txt
Dhantri-0.1.dist-info/RECORD
