Metadata-Version: 2.1
Name: Dhantri
Version: 0.1
Summary: This function calculates and displays the attendance percentage and determines if a student is allowed to sit in an exam based on their attendance
Author: yeswanth vinay
Author-email: yeswanthvinay562@gmail.com
Classifier: Programming Language :: Python :: 3
Classifier: License :: OSI Approved :: MIT License
Classifier: Operating System :: OS Independent
License-File: LICENCE.txt
